int/test_integration.py
patchwork/client/kafka/__init__.py
patchwork/client/kafka/common.py
patchwork/client/kafka/publisher.py
patchwork/client/kafka/subscriber.py
tests/__init__.py
tests/conftest.py
tests/test_clientkafka.py
patchwork_client_kafka-0.2.10.dist-info/LICENSE
patchwork_client_kafka-0.2.10.dist-info/METADATA
patchwork_client_kafka-0.2.10.dist-info/WHEEL
patchwork_client_kafka-0.2.10.dist-info/top_level.txt
patchwork_client_kafka-0.2.10.dist-info/RECORD
