Metadata-Version: 2.1
Name: patchwork-client-kafka
Version: 0.2.10
Summary: Kafka client for Patchwork - The distributed asynchronous microframework
Home-page: 
Author: Pawel Pecio
Author-email: 
Classifier: Development Status :: 5 - Production/Stable
Classifier: License :: OSI Approved :: MIT License
Classifier: Operating System :: POSIX :: Linux
Classifier: Programming Language :: Python :: 3.8
Classifier: Programming Language :: Python :: 3.9
Classifier: Programming Language :: Python :: 3.10
Classifier: Programming Language :: Python :: Implementation :: CPython
Classifier: Topic :: Software Development :: Libraries :: Application Frameworks
License-File: LICENSE
Requires-Dist: aiokafka <0.9.0,>=0.7.2
Requires-Dist: patchwork-core ~=0.2
Requires-Dist: humanize
Requires-Dist: pytz
